fdutil/__init__.py
fdutil/_metadata.py
fdutil/crossplatform_startfile.py
fdutil/dict_tools.py
fdutil/encoded_file.py
fdutil/file_utils.py
fdutil/html.py
fdutil/list_tools.py
fdutil/parse_json.py
fdutil/parse_xml.py
fdutil/parse_yaml.py
fdutil/path_tools.py
fdutil/safe.py
fdutil/simple_excel_to_jira.py
fdutil/string_generator.py
fdutil/string_scanner.py
fdutil/string_tools.py
fdutil/tree_search.py
fdutil/type_check.py
fdutil/watchfolder.py
fdutil/windows_usb_drives.py
fdutil/data/__init__.py
fdutil/data/dict/__init__.py
fdutil/data/dict/diff.py
fdutil/data/store/__init__.py
fdutil/data/store/_constants.py
fdutil/data/store/data_store.py
fdutil/resources/__init__.py
fdutil/resources/clickable_popover.js
fdutil/resources/enable_tooltip_snippet.js
fdutil/resources/open_document_snippet.js
fdutil/unittests/__init__.py
fdutil/unittests/test_dict_tools.py
fdutil/unittests/test_encoded_file.py
fdutil/unittests/test_file_utils.py
fdutil/unittests/test_list_tools.py
fdutil/unittests/test_parse_json.py
fdutil/unittests/test_parse_xml.py
fdutil/unittests/test_parse_yaml.py
fdutil/unittests/test_string_tools.py
fdutil/unittests/test_tree_search.py
fdutil/unittests/test_type_check.py
fdutil-1.16.1.dist-info/LICENSE.txt
fdutil-1.16.1.dist-info/METADATA
fdutil-1.16.1.dist-info/WHEEL
fdutil-1.16.1.dist-info/entry_points.txt
fdutil-1.16.1.dist-info/top_level.txt
fdutil-1.16.1.dist-info/RECORD
