Metadata-Version: 2.1
Name: fdutil
Version: 1.16.1
Summary: A collection of python utilities for manipulating files and data.
Home-page: https://bitbucket.org/davisowb/fdutil.git
Author: Oli Davis, Hywel Thomas
Author-email: oli.davis@me.com, hywel.thomas@mac.com
License: MIT
Download-URL: https://bitbucket.org/davisowb/fdutil.git/get/1.16.1.tar
Keywords: example
Platform: UNKNOWN
Classifier: Development Status :: 3 - Alpha
Classifier: Intended Audience :: Developers
Classifier: License :: OSI Approved :: MIT License
Classifier: Programming Language :: Python :: 2
Classifier: Programming Language :: Python :: 2.7
Classifier: Programming Language :: Python :: 3
Classifier: Programming Language :: Python :: 3.6
Classifier: Topic :: Utilities
License-File: LICENSE.txt
Requires-Dist: pip (>=18.1)
Requires-Dist: future (>=0.16.0)
Requires-Dist: ruamel.yaml (>=0.15.35)
Requires-Dist: pyperclip (>=1.5.27)
Requires-Dist: logging-helper (>=1.7.0)
Requires-Dist: configurationutil (>=3.7.0)
Requires-Dist: conversionutil (>=1.1.0)
Requires-Dist: stateutil (>=1.4.0)
Requires-Dist: watchdog (>=0.8.3)
Requires-Dist: dominate (>=2.3.1)
Requires-Dist: pywin32 (>=223) ; platform_system == "Windows"
Provides-Extra: test
